pyTRLCConverter/__init__.py
pyTRLCConverter/__main__.py
pyTRLCConverter/abstract_converter.py
pyTRLCConverter/base_converter.py
pyTRLCConverter/docx_converter.py
pyTRLCConverter/dump_converter.py
pyTRLCConverter/item_walker.py
pyTRLCConverter/logger.py
pyTRLCConverter/markdown_converter.py
pyTRLCConverter/plantuml.py
pyTRLCConverter/ret.py
pyTRLCConverter/rst_converter.py
pyTRLCConverter/translator.py
pyTRLCConverter/trlc_helper.py
pyTRLCConverter/version.py
pytrlcconverter-1.0.2.dist-info/licenses/LICENSE
pytrlcconverter-1.0.2.dist-info/METADATA
pytrlcconverter-1.0.2.dist-info/WHEEL
pytrlcconverter-1.0.2.dist-info/entry_points.txt
pytrlcconverter-1.0.2.dist-info/top_level.txt
pytrlcconverter-1.0.2.dist-info/RECORD
