Metadata-Version: 2.4
Name: pyTRLCConverter
Version: 1.0.2
Summary: Supports the conversion from TRLC files to other formats.
Author-email: Andreas Merkle <andreas.merkle@newtec.de>
License-Expression: GPL-3.0-only
Project-URL: documentation, https://github.com/NewTec-GmbH/pyTRLCConverter
Project-URL: repository, https://github.com/NewTec-GmbH/pyTRLCConverter
Project-URL: tracker, https://github.com/NewTec-GmbH/pyTRLCConverter/issues
Classifier: Operating System :: OS Independent
Classifier: Programming Language :: Python :: 3.10
Classifier: Programming Language :: Python :: 3.11
Classifier: Programming Language :: Python :: 3.12
Requires-Python: >=3.10
License-File: LICENSE
Requires-Dist: toml>=0.10.2
Requires-Dist: requests>=2.32.0
Requires-Dist: python-docx>=1.1.2
Requires-Dist: trlc>=2.0.2
Provides-Extra: dev
Requires-Dist: toml>=0.10.2; extra == "dev"
Requires-Dist: tomlkit>=0.13.2; extra == "dev"
Requires-Dist: pylint>=3.3.1; extra == "dev"
Requires-Dist: Sphinx>=8.1.3; extra == "dev"
Requires-Dist: sphinx-favicon>=1.0.1; extra == "dev"
Requires-Dist: sphinx-rtd-theme>=3.0.1; extra == "dev"
Requires-Dist: pyinstaller>=6.11.1; extra == "dev"
Requires-Dist: pytest>=8.3.3; extra == "dev"
Requires-Dist: pytest-cov>=6.0.0; extra == "dev"
Requires-Dist: myst-parser>=4.0.0; extra == "dev"
Requires-Dist: sphinxcontrib-plantuml>=0.30; extra == "dev"
Requires-Dist: m2r>=0.3.1; extra == "dev"
Requires-Dist: bmw-lobster>=0.13.2; extra == "dev"
Dynamic: license-file
